{"entries": [{"id": 1, "name": "Luke 1", "paid": "YES", "team": "\ud83c\udde7\ud83c\uddea Belgium", "status": "ACTIVE"}, {"id": 2, "name": "Clark 1", "paid": "YES", "team": "\ud83c\uddf9\ud83c\uddf3 Tunisia", "status": "ACTIVE"}, {"id": 3, "name": "Ben 1", "paid": "YES", "team": "\ud83c\udde6\ud83c\uddf7 Argentina", "status": "ACTIVE"}, {"id": 4, "name": "Wardy 1", "paid": "YES", "team": "\ud83c\uddef\ud83c\uddf5 Japan", "status": "ACTIVE"}, {"id": 5, "name": "Shanty 1", "paid": "YES", "team": "\ud83c\uddf3\ud83c\uddff New Zealand", "status": "ACTIVE"}, {"id": 6, "name": "Shanty 2", "paid": "YES", "team": "\ud83c\uddf6\ud83c\udde6 Qatar", "status": "ACTIVE"}, {"id": 7, "name": "Wardy 2", "paid": "YES", "team": "\ud83c\uddf2\ud83c\udde6 Morocco", "status": "ACTIVE"}, {"id": 8, "name": "Wardys uncle 1", "paid": "YES", "team": "\ud83c\udde8\ud83c\udded Switzerland", "status": "ACTIVE"}, {"id": 9, "name": "Luke 2", "paid": "YES", "team": "\ud83c\udde8\ud83c\uddf4 Colombia", "status": "ACTIVE"}, {"id": 10, "name": "Ben 2", "paid": "YES", "team": "\ud83c\uddf3\ud83c\uddf1 Netherlands", "status": "ACTIVE"}, {"id": 11, "name": "Lucy 1", "paid": "YES", "team": "\ud83c\uddff\ud83c\udde6 South Africa", "status": "ACTIVE"}, {"id": 12, "name": "Cat 1", "paid": "YES", "team": "\ud83c\uddf5\ud83c\udde6 Panama", "status": "ACTIVE"}, {"id": 13, "name": "Baggins 1", "paid": "YES", "team": "\ud83c\udde8\ud83c\udde6 Canada", "status": "ACTIVE"}, {"id": 14, "name": "Worm 1", "paid": "YES", "team": "\ud83c\uddeb\ud83c\uddf7 France", "status": "ACTIVE"}, {"id": 15, "name": "Woody 1", "paid": "YES", "team": "\ud83c\udde7\ud83c\uddf7 Brazil", "status": "ACTIVE"}, {"id": 16, "name": "Woody 2", "paid": "YES", "team": "\ud83c\udde7\ud83c\udde6 Bosnia & Herz.", "status": "ACTIVE"}, {"id": 17, "name": "Leo 1", "paid": "YES", "team": "\ud83c\udde9\ud83c\uddea Germany", "status": "ACTIVE"}, {"id": 18, "name": "Jack 1", "paid": "YES", "team": "\ud83c\udff4\udb40\udc67\udb40\udc62\udb40\udc65\udb40\udc6e\udb40\udc67\udb40\udc7f England", "status": "ACTIVE"}, {"id": 19, "name": "Jack 2", "paid": "YES", "team": "\ud83c\udde8\ud83c\uddee Ivory Coast", "status": "ACTIVE"}, {"id": 20, "name": "Goody 1", "paid": "YES", "team": "\ud83c\uddee\ud83c\uddf7 Iran", "status": "ACTIVE"}, {"id": 21, "name": "Goody 2", "paid": "YES", "team": "\ud83c\uddea\ud83c\udde8 Ecuador", "status": "ACTIVE"}, {"id": 22, "name": "Reece 1", "paid": "YES", "team": "\ud83c\udde6\ud83c\uddfa Australia", "status": "ACTIVE"}, {"id": 23, "name": "Reece 2", "paid": "YES", "team": "\ud83c\uddea\ud83c\uddf8 Spain", "status": "ACTIVE"}, {"id": 24, "name": "Clark 2", "paid": "YES", "team": "\ud83c\uddf5\ud83c\uddfe Paraguay", "status": "ACTIVE"}, {"id": 25, "name": "Luke 3", "paid": "YES", "team": "\ud83c\uddf8\ud83c\uddea Sweden", "status": "ACTIVE"}, {"id": 26, "name": "Clark 3", "paid": "YES", "team": "\ud83c\udde8\ud83c\uddfb Cape Verde", "status": "ACTIVE"}, {"id": 27, "name": "Ben 3", "paid": "YES", "team": "\ud83c\uddf2\ud83c\uddfd Mexico", "status": "ACTIVE"}, {"id": 28, "name": "Wardy 3", "paid": "YES", "team": "\ud83c\uddf5\ud83c\uddf9 Portugal", "status": "ACTIVE"}, {"id": 29, "name": "Shanty 3", "paid": "YES", "team": "\ud83c\uddf8\ud83c\uddf3 Senegal", "status": "ACTIVE"}, {"id": 30, "name": "Shanty 4", "paid": "YES", "team": "\ud83c\uddec\ud83c\udded Ghana", "status": "ACTIVE"}, {"id": 31, "name": "Wardy 4", "paid": "YES", "team": "\ud83c\uddf3\ud83c\uddf4 Norway", "status": "ACTIVE"}, {"id": 32, "name": "Wardys uncle 2", "paid": "YES", "team": "\ud83c\uddee\ud83c\uddf6 Iraq", "status": "ACTIVE"}, {"id": 33, "name": "Luke 4", "paid": "YES", "team": "\ud83c\uddf8\ud83c\udde6 Saudi Arabia", "status": "ACTIVE"}, {"id": 34, "name": "Ben 4", "paid": "YES", "team": "\ud83c\uddfa\ud83c\uddfe Uruguay", "status": "ACTIVE"}, {"id": 35, "name": "Lucy 2", "paid": "YES", "team": "\ud83c\udde8\ud83c\uddff Czechia", "status": "ACTIVE"}, {"id": 36, "name": "Cat 2", "paid": "YES", "team": "\ud83c\uddef\ud83c\uddf4 Jordan", "status": "ACTIVE"}, {"id": 37, "name": "Baggins 2", "paid": "YES", "team": "\ud83c\uddfa\ud83c\uddf8 USA", "status": "ACTIVE"}, {"id": 38, "name": "Worm 2", "paid": "YES", "team": "\ud83c\uddfa\ud83c\uddff Uzbekistan", "status": "ACTIVE"}, {"id": 39, "name": "Woody 3", "paid": "YES", "team": "\ud83c\udded\ud83c\uddf9 Haiti", "status": "ACTIVE"}, {"id": 40, "name": "Woody 4", "paid": "YES", "team": "\ud83c\udff4\udb40\udc67\udb40\udc62\udb40\udc73\udb40\udc63\udb40\udc74\udb40\udc7f Scotland", "status": "ACTIVE"}, {"id": 41, "name": "Leo 2", "paid": "YES", "team": "\ud83c\udde6\ud83c\uddf9 Austria", "status": "ACTIVE"}, {"id": 42, "name": "Jack 3", "paid": "YES", "team": "\ud83c\udded\ud83c\uddf7 Croatia", "status": "ACTIVE"}, {"id": 43, "name": "Jack 4", "paid": "YES", "team": "\ud83c\uddf0\ud83c\uddf7 South Korea", "status": "ACTIVE"}, {"id": 44, "name": "Goody 3", "paid": "YES", "team": "\ud83c\udde8\ud83c\uddfc Cura\u00e7ao", "status": "ACTIVE"}, {"id": 45, "name": "Goody 4", "paid": "YES", "team": "\ud83c\udde9\ud83c\uddff Algeria", "status": "ACTIVE"}, {"id": 46, "name": "Reece 3", "paid": "YES", "team": "\ud83c\udde8\ud83c\udde9 DR Congo", "status": "ACTIVE"}, {"id": 47, "name": "Reece 4", "paid": "YES", "team": "\ud83c\uddea\ud83c\uddec Egypt", "status": "ACTIVE"}, {"id": 48, "name": "Clark 4", "paid": "YES", "team": "\ud83c\uddf9\ud83c\uddf7 Turkey", "status": "ACTIVE"}], "bracket": [{"id": "R32_1", "round": "R32", "num": 1, "t1": "\ud83c\uddff\ud83c\udde6 South Africa", "t2": "\ud83c\udde8\ud83c\udde6 Canada", "winner": "\ud83c\udde8\ud83c\udde6 Canada", "score1": "0", "score2": "1", "played": true}, {"id": "R32_2", "round": "R32", "num": 2, "t1": "\ud83c\udde7\ud83c\uddf7 Brazil", "t2": "\ud83c\uddef\ud83c\uddf5 Japan", "winner": "\ud83c\udde7\ud83c\uddf7 Brazil", "score1": "2", "score2": "1", "played": true}, {"id": "R32_3", "round": "R32", "num": 3, "t1": "\ud83c\udde9\ud83c\uddea Germany", "t2": "\ud83c\uddf5\ud83c\uddfe Paraguay", "winner": "\ud83c\uddf5\ud83c\uddfe Paraguay", "score1": "1", "score2": "1", "played": true}, {"id": "R32_4", "round": "R32", "num": 4, "t1": "\ud83c\uddf3\ud83c\uddf1 Netherlands", "t2": "\ud83c\uddf2\ud83c\udde6 Morocco", "winner": "\ud83c\uddf2\ud83c\udde6 Morocco", "score1": "1", "score2": "1", "played": true}, {"id": "R32_5", "round": "R32", "num": 5, "t1": "\ud83c\udde8\ud83c\uddee Ivory Coast", "t2": "\ud83c\uddf3\ud83c\uddf4 Norway", "winner": "\ud83c\uddf3\ud83c\uddf4 Norway", "score1": "1", "score2": "2", "played": true}, {"id": "R32_6", "round": "R32", "num": 6, "t1": "\ud83c\uddeb\ud83c\uddf7 France", "t2": "\ud83c\uddf8\ud83c\uddea Sweden", "winner": "\ud83c\uddeb\ud83c\uddf7 France", "score1": "3", "score2": "0", "played": true}, {"id": "R32_7", "round": "R32", "num": 7, "t1": "\ud83c\uddf2\ud83c\uddfd Mexico", "t2": "\ud83c\uddea\ud83c\udde8 Ecuador", "winner": "\ud83c\uddf2\ud83c\uddfd Mexico", "score1": "2", "score2": "0", "played": true}, {"id": "R32_8", "round": "R32", "num": 8, "t1": "\ud83c\udff4\udb40\udc67\udb40\udc62\udb40\udc65\udb40\udc6e\udb40\udc67\udb40\udc7f England", "t2": "\ud83c\udde8\ud83c\udde9 DR Congo", "winner": "\ud83c\udff4\udb40\udc67\udb40\udc62\udb40\udc65\udb40\udc6e\udb40\udc67\udb40\udc7f England", "score1": "2", "score2": "1", "played": true}, {"id": "R32_9", "round": "R32", "num": 9, "t1": "\ud83c\udde7\ud83c\uddea Belgium", "t2": "\ud83c\uddf8\ud83c\uddf3 Senegal", "winner": "\ud83c\udde7\ud83c\uddea Belgium", "score1": "3", "score2": "2", "played": true}, {"id": "R32_10", "round": "R32", "num": 10, "t1": "\ud83c\uddfa\ud83c\uddf8 USA", "t2": "\ud83c\udde7\ud83c\udde6 Bosnia & Herz.", "winner": "\ud83c\uddfa\ud83c\uddf8 USA", "score1": "2", "score2": "0", "played": true}, {"id": "R32_11", "round": "R32", "num": 11, "t1": "\ud83c\uddea\ud83c\uddf8 Spain", "t2": "\ud83c\udde6\ud83c\uddf9 Austria", "winner": "\ud83c\uddea\ud83c\uddf8 Spain", "score1": "3", "score2": "0", "played": true}, {"id": "R32_12", "round": "R32", "num": 12, "t1": "\ud83c\uddf5\ud83c\uddf9 Portugal", "t2": "\ud83c\udded\ud83c\uddf7 Croatia", "winner": "\ud83c\uddf5\ud83c\uddf9 Portugal", "score1": "2", "score2": "1", "played": true}, {"id": "R32_13", "round": "R32", "num": 13, "t1": "\ud83c\udde8\ud83c\udded Switzerland", "t2": "\ud83c\udde9\ud83c\uddff Algeria", "winner": "\ud83c\udde8\ud83c\udded Switzerland", "score1": "2", "score2": "0", "played": true}, {"id": "R32_14", "round": "R32", "num": 14, "t1": "\ud83c\udde6\ud83c\uddfa Australia", "t2": "\ud83c\uddea\ud83c\uddec Egypt", "winner": "\ud83c\uddea\ud83c\uddec Egypt", "score1": "1", "score2": "1", "played": true}, {"id": "R32_15", "round": "R32", "num": 15, "t1": "\ud83c\udde6\ud83c\uddf7 Argentina", "t2": "\ud83c\udde8\ud83c\uddfb Cape Verde", "winner": "\ud83c\udde6\ud83c\uddf7 Argentina", "score1": "3", "score2": "2", "played": true}, {"id": "R32_16", "round": "R32", "num": 16, "t1": "\ud83c\udde8\ud83c\uddf4 Colombia", "t2": "\ud83c\uddec\ud83c\udded Ghana", "winner": "\ud83c\udde8\ud83c\uddf4 Colombia", "score1": "1", "score2": "0", "played": true}, {"id": "R16_1", "round": "R16", "num": 1, "t1": "\ud83c\uddf2\ud83c\udde6 Morocco", "t2": "\ud83c\udde8\ud83c\udde6 Canada", "winner": "\ud83c\uddf2\ud83c\udde6 Morocco", "score1": "3", "score2": "0", "played": true}, {"id": "R16_2", "round": "R16", "num": 2, "t1": "\ud83c\uddeb\ud83c\uddf7 France", "t2": "\ud83c\uddf5\ud83c\uddfe Paraguay", "winner": "\ud83c\uddeb\ud83c\uddf7 France", "score1": "1", "score2": "0", "played": true}, {"id": "R16_3", "round": "R16", "num": 3, "t1": "\ud83c\udde7\ud83c\uddf7 Brazil", "t2": "\ud83c\uddf3\ud83c\uddf4 Norway", "winner": "\ud83c\uddf3\ud83c\uddf4 Norway", "score1": "1", "score2": "2", "played": true}, {"id": "R16_4", "round": "R16", "num": 4, "t1": "\ud83c\uddf2\ud83c\uddfd Mexico", "t2": "\ud83c\udff4\udb40\udc67\udb40\udc62\udb40\udc65\udb40\udc6e\udb40\udc67\udb40\udc7f England", "winner": "\ud83c\udff4\udb40\udc67\udb40\udc62\udb40\udc65\udb40\udc6e\udb40\udc67\udb40\udc7f England", "score1": "2", "score2": "3", "played": true}, {"id": "R16_5", "round": "R16", "num": 5, "t1": "\ud83c\uddea\ud83c\uddf8 Spain", "t2": "\ud83c\uddf5\ud83c\uddf9 Portugal", "winner": "\ud83c\uddea\ud83c\uddf8 Spain", "score1": "1", "score2": "0", "played": true}, {"id": "R16_6", "round": "R16", "num": 6, "t1": "\ud83c\uddfa\ud83c\uddf8 USA", "t2": "\ud83c\udde7\ud83c\uddea Belgium", "winner": "\ud83c\udde7\ud83c\uddea Belgium", "score1": "1", "score2": "4", "played": true}, {"id": "R16_7", "round": "R16", "num": 7, "t1": "\ud83c\udde6\ud83c\uddf7 Argentina", "t2": "\ud83c\uddea\ud83c\uddec Egypt", "winner": "\ud83c\udde6\ud83c\uddf7 Argentina", "score1": "3", "score2": "2", "played": true}, {"id": "R16_8", "round": "R16", "num": 8, "t1": "\ud83c\udde8\ud83c\udded Switzerland", "t2": "\ud83c\udde8\ud83c\uddf4 Colombia", "winner": "\ud83c\udde8\ud83c\udded Switzerland", "score1": "0", "score2": "0", "played": true}, {"id": "QF_1", "round": "QF", "num": 1, "t1": "\ud83c\uddf2\ud83c\udde6 Morocco", "t2": "\ud83c\uddeb\ud83c\uddf7 France", "winner": "\ud83c\uddeb\ud83c\uddf7 France", "score1": "0", "score2": "2", "played": true}, {"id": "QF_2", "round": "QF", "num": 2, "t1": "\ud83c\uddf3\ud83c\uddf4 Norway", "t2": "\ud83c\udff4\udb40\udc67\udb40\udc62\udb40\udc65\udb40\udc6e\udb40\udc67\udb40\udc7f England", "winner": "\ud83c\udff4\udb40\udc67\udb40\udc62\udb40\udc65\udb40\udc6e\udb40\udc67\udb40\udc7f England", "score1": "1", "score2": "2", "played": true}, {"id": "QF_3", "round": "QF", "num": 3, "t1": "\ud83c\uddea\ud83c\uddf8 Spain", "t2": "\ud83c\udde7\ud83c\uddea Belgium", "winner": "\ud83c\uddea\ud83c\uddf8 Spain", "score1": "2", "score2": "1", "played": true}, {"id": "QF_4", "round": "QF", "num": 4, "t1": "\ud83c\udde6\ud83c\uddf7 Argentina", "t2": "\ud83c\udde8\ud83c\udded Switzerland", "winner": "\ud83c\udde6\ud83c\uddf7 Argentina", "score1": "3", "score2": "1", "played": true}, {"id": "SF_1", "round": "SF", "num": 1, "t1": "\ud83c\uddeb\ud83c\uddf7 France", "t2": "\ud83c\uddea\ud83c\uddf8 Spain", "winner": "", "score1": "", "score2": "", "played": false}, {"id": "SF_2", "round": "SF", "num": 2, "t1": "\ud83c\udff4\udb40\udc67\udb40\udc62\udb40\udc65\udb40\udc6e\udb40\udc67\udb40\udc7f England", "t2": "\ud83c\udde6\ud83c\uddf7 Argentina", "winner": "", "score1": "", "score2": "", "played": false}, {"id": "3P_1", "round": "3P", "num": 1, "t1": "", "t2": "", "winner": ""}, {"id": "FIN_1", "round": "FIN", "num": 1, "t1": "", "t2": "", "winner": ""}], "groupMatches": [{"id": "GA_1", "group": "A", "team1": "\ud83c\uddf2\ud83c\uddfd Mexico", "team2": "\ud83c\uddff\ud83c\udde6 South Africa", "score1": "2", "score2": "0", "played": true}, {"id": "GA_2", "group": "A", "team1": "\ud83c\uddf2\ud83c\uddfd Mexico", "team2": "\ud83c\uddf0\ud83c\uddf7 South Korea", "score1": "1", "score2": "0", "played": true}, {"id": "GA_3", "group": "A", "team1": "\ud83c\uddf2\ud83c\uddfd Mexico", "team2": "\ud83c\udde8\ud83c\uddff Czechia", "score1": "3", "score2": "0", "played": true}, {"id": "GA_4", "group": "A", "team1": "\ud83c\uddff\ud83c\udde6 South Africa", "team2": "\ud83c\uddf0\ud83c\uddf7 South Korea", "score1": "1", "score2": "0", "played": true}, {"id": "GA_5", "group": "A", "team1": "\ud83c\uddff\ud83c\udde6 South Africa", "team2": "\ud83c\udde8\ud83c\uddff Czechia", "score1": "1", "score2": "1", "played": true}, {"id": "GA_6", "group": "A", "team1": "\ud83c\uddf0\ud83c\uddf7 South Korea", "team2": "\ud83c\udde8\ud83c\uddff Czechia", "score1": "2", "score2": "1", "played": true}, {"id": "GB_1", "group": "B", "team1": "\ud83c\udde8\ud83c\udde6 Canada", "team2": "\ud83c\udde7\ud83c\udde6 Bosnia & Herz.", "score1": "1", "score2": "1", "played": true}, {"id": "GB_2", "group": "B", "team1": "\ud83c\udde8\ud83c\udde6 Canada", "team2": "\ud83c\uddf6\ud83c\udde6 Qatar", "score1": "6", "score2": "0", "played": true}, {"id": "GB_3", "group": "B", "team1": "\ud83c\udde8\ud83c\udde6 Canada", "team2": "\ud83c\udde8\ud83c\udded Switzerland", "score1": "1", "score2": "2", "played": true}, {"id": "GB_4", "group": "B", "team1": "\ud83c\udde7\ud83c\udde6 Bosnia & Herz.", "team2": "\ud83c\uddf6\ud83c\udde6 Qatar", "score1": "3", "score2": "1", "played": true}, {"id": "GB_5", "group": "B", "team1": "\ud83c\udde7\ud83c\udde6 Bosnia & Herz.", "team2": "\ud83c\udde8\ud83c\udded Switzerland", "score1": "1", "score2": "4", "played": true}, {"id": "GB_6", "group": "B", "team1": "\ud83c\uddf6\ud83c\udde6 Qatar", "team2": "\ud83c\udde8\ud83c\udded Switzerland", "score1": "1", "score2": "1", "played": true}, {"id": "GC_1", "group": "C", "team1": "\ud83c\udde7\ud83c\uddf7 Brazil", "team2": "\ud83c\uddf2\ud83c\udde6 Morocco", "score1": "1", "score2": "1", "played": true}, {"id": "GC_2", "group": "C", "team1": "\ud83c\udde7\ud83c\uddf7 Brazil", "team2": "\ud83c\udded\ud83c\uddf9 Haiti", "score1": "3", "score2": "0", "played": true}, {"id": "GC_3", "group": "C", "team1": "\ud83c\udde7\ud83c\uddf7 Brazil", "team2": "\ud83c\udff4\udb40\udc67\udb40\udc62\udb40\udc73\udb40\udc63\udb40\udc74\udb40\udc7f Scotland", "score1": "3", "score2": "0", "played": true}, {"id": "GC_4", "group": "C", "team1": "\ud83c\uddf2\ud83c\udde6 Morocco", "team2": "\ud83c\udded\ud83c\uddf9 Haiti", "score1": "4", "score2": "2", "played": true}, {"id": "GC_5", "group": "C", "team1": "\ud83c\uddf2\ud83c\udde6 Morocco", "team2": "\ud83c\udff4\udb40\udc67\udb40\udc62\udb40\udc73\udb40\udc63\udb40\udc74\udb40\udc7f Scotland", "score1": "1", "score2": "0", "played": true}, {"id": "GC_6", "group": "C", "team1": "\ud83c\udded\ud83c\uddf9 Haiti", "team2": "\ud83c\udff4\udb40\udc67\udb40\udc62\udb40\udc73\udb40\udc63\udb40\udc74\udb40\udc7f Scotland", "score1": "0", "score2": "1", "played": true}, {"id": "GD_1", "group": "D", "team1": "\ud83c\uddfa\ud83c\uddf8 USA", "team2": "\ud83c\uddf5\ud83c\uddfe Paraguay", "score1": "4", "score2": "1", "played": true}, {"id": "GD_2", "group": "D", "team1": "\ud83c\uddfa\ud83c\uddf8 USA", "team2": "\ud83c\udde6\ud83c\uddfa Australia", "score1": "2", "score2": "0", "played": true}, {"id": "GD_3", "group": "D", "team1": "\ud83c\uddfa\ud83c\uddf8 USA", "team2": "\ud83c\uddf9\ud83c\uddf7 Turkey", "score1": "2", "score2": "3", "played": true}, {"id": "GD_4", "group": "D", "team1": "\ud83c\uddf5\ud83c\uddfe Paraguay", "team2": "\ud83c\udde6\ud83c\uddfa Australia", "score1": "0", "score2": "0", "played": true}, {"id": "GD_5", "group": "D", "team1": "\ud83c\uddf5\ud83c\uddfe Paraguay", "team2": "\ud83c\uddf9\ud83c\uddf7 Turkey", "score1": "0", "score2": "1", "played": true}, {"id": "GD_6", "group": "D", "team1": "\ud83c\udde6\ud83c\uddfa Australia", "team2": "\ud83c\uddf9\ud83c\uddf7 Turkey", "score1": "2", "score2": "0", "played": true}, {"id": "GE_1", "group": "E", "team1": "\ud83c\udde9\ud83c\uddea Germany", "team2": "\ud83c\udde8\ud83c\uddfc Cura\u00e7ao", "score1": "7", "score2": "1", "played": true}, {"id": "GE_2", "group": "E", "team1": "\ud83c\udde9\ud83c\uddea Germany", "team2": "\ud83c\udde8\ud83c\uddee Ivory Coast", "score1": "2", "score2": "1", "played": true}, {"id": "GE_3", "group": "E", "team1": "\ud83c\udde9\ud83c\uddea Germany", "team2": "\ud83c\uddea\ud83c\udde8 Ecuador", "score1": "1", "score2": "2", "played": true}, {"id": "GE_4", "group": "E", "team1": "\ud83c\udde8\ud83c\uddfc Cura\u00e7ao", "team2": "\ud83c\udde8\ud83c\uddee Ivory Coast", "score1": "0", "score2": "1", "played": true}, {"id": "GE_5", "group": "E", "team1": "\ud83c\udde8\ud83c\uddfc Cura\u00e7ao", "team2": "\ud83c\uddea\ud83c\udde8 Ecuador", "score1": "0", "score2": "0", "played": true}, {"id": "GE_6", "group": "E", "team1": "\ud83c\udde8\ud83c\uddee Ivory Coast", "team2": "\ud83c\uddea\ud83c\udde8 Ecuador", "score1": "1", "score2": "0", "played": true}, {"id": "GF_1", "group": "F", "team1": "\ud83c\uddf3\ud83c\uddf1 Netherlands", "team2": "\ud83c\uddef\ud83c\uddf5 Japan", "score1": "2", "score2": "2", "played": true}, {"id": "GF_2", "group": "F", "team1": "\ud83c\uddf3\ud83c\uddf1 Netherlands", "team2": "\ud83c\uddf8\ud83c\uddea Sweden", "score1": "5", "score2": "1", "played": true}, {"id": "GF_3", "group": "F", "team1": "\ud83c\uddf3\ud83c\uddf1 Netherlands", "team2": "\ud83c\uddf9\ud83c\uddf3 Tunisia", "score1": "3", "score2": "1", "played": true}, {"id": "GF_4", "group": "F", "team1": "\ud83c\uddef\ud83c\uddf5 Japan", "team2": "\ud83c\uddf8\ud83c\uddea Sweden", "score1": "1", "score2": "1", "played": true}, {"id": "GF_5", "group": "F", "team1": "\ud83c\uddef\ud83c\uddf5 Japan", "team2": "\ud83c\uddf9\ud83c\uddf3 Tunisia", "score1": "4", "score2": "0", "played": true}, {"id": "GF_6", "group": "F", "team1": "\ud83c\uddf8\ud83c\uddea Sweden", "team2": "\ud83c\uddf9\ud83c\uddf3 Tunisia", "score1": "5", "score2": "1", "played": true}, {"id": "GG_1", "group": "G", "team1": "\ud83c\udde7\ud83c\uddea Belgium", "team2": "\ud83c\uddea\ud83c\uddec Egypt", "score1": "1", "score2": "1", "played": true}, {"id": "GG_2", "group": "G", "team1": "\ud83c\udde7\ud83c\uddea Belgium", "team2": "\ud83c\uddee\ud83c\uddf7 Iran", "score1": "0", "score2": "0", "played": true}, {"id": "GG_3", "group": "G", "team1": "\ud83c\udde7\ud83c\uddea Belgium", "team2": "\ud83c\uddf3\ud83c\uddff New Zealand", "score1": "5", "score2": "1", "played": true}, {"id": "GG_4", "group": "G", "team1": "\ud83c\uddea\ud83c\uddec Egypt", "team2": "\ud83c\uddee\ud83c\uddf7 Iran", "score1": "1", "score2": "1", "played": true}, {"id": "GG_5", "group": "G", "team1": "\ud83c\uddea\ud83c\uddec Egypt", "team2": "\ud83c\uddf3\ud83c\uddff New Zealand", "score1": "3", "score2": "1", "played": true}, {"id": "GG_6", "group": "G", "team1": "\ud83c\uddee\ud83c\uddf7 Iran", "team2": "\ud83c\uddf3\ud83c\uddff New Zealand", "score1": "2", "score2": "2", "played": true}, {"id": "GH_1", "group": "H", "team1": "\ud83c\uddea\ud83c\uddf8 Spain", "team2": "\ud83c\udde8\ud83c\uddfb Cape Verde", "score1": "0", "score2": "0", "played": true}, {"id": "GH_2", "group": "H", "team1": "\ud83c\uddea\ud83c\uddf8 Spain", "team2": "\ud83c\uddf8\ud83c\udde6 Saudi Arabia", "score1": "4", "score2": "0", "played": true}, {"id": "GH_3", "group": "H", "team1": "\ud83c\uddea\ud83c\uddf8 Spain", "team2": "\ud83c\uddfa\ud83c\uddfe Uruguay", "score1": "1", "score2": "0", "played": true}, {"id": "GH_4", "group": "H", "team1": "\ud83c\udde8\ud83c\uddfb Cape Verde", "team2": "\ud83c\uddf8\ud83c\udde6 Saudi Arabia", "score1": "0", "score2": "0", "played": true}, {"id": "GH_5", "group": "H", "team1": "\ud83c\udde8\ud83c\uddfb Cape Verde", "team2": "\ud83c\uddfa\ud83c\uddfe Uruguay", "score1": "2", "score2": "2", "played": true}, {"id": "GH_6", "group": "H", "team1": "\ud83c\uddf8\ud83c\udde6 Saudi Arabia", "team2": "\ud83c\uddfa\ud83c\uddfe Uruguay", "score1": "1", "score2": "1", "played": true}, {"id": "GI_1", "group": "I", "team1": "\ud83c\uddeb\ud83c\uddf7 France", "team2": "\ud83c\uddf8\ud83c\uddf3 Senegal", "score1": "3", "score2": "1", "played": true}, {"id": "GI_2", "group": "I", "team1": "\ud83c\uddeb\ud83c\uddf7 France", "team2": "\ud83c\uddee\ud83c\uddf6 Iraq", "score1": "3", "score2": "0", "played": true}, {"id": "GI_3", "group": "I", "team1": "\ud83c\uddeb\ud83c\uddf7 France", "team2": "\ud83c\uddf3\ud83c\uddf4 Norway", "score1": "4", "score2": "1", "played": true}, {"id": "GI_4", "group": "I", "team1": "\ud83c\uddf8\ud83c\uddf3 Senegal", "team2": "\ud83c\uddee\ud83c\uddf6 Iraq", "score1": "5", "score2": "0", "played": true}, {"id": "GI_5", "group": "I", "team1": "\ud83c\uddf8\ud83c\uddf3 Senegal", "team2": "\ud83c\uddf3\ud83c\uddf4 Norway", "score1": "2", "score2": "3", "played": true}, {"id": "GI_6", "group": "I", "team1": "\ud83c\uddee\ud83c\uddf6 Iraq", "team2": "\ud83c\uddf3\ud83c\uddf4 Norway", "score1": "1", "score2": "4", "played": true}, {"id": "GJ_1", "group": "J", "team1": "\ud83c\udde6\ud83c\uddf7 Argentina", "team2": "\ud83c\udde9\ud83c\uddff Algeria", "score1": "3", "score2": "0", "played": true}, {"id": "GJ_2", "group": "J", "team1": "\ud83c\udde6\ud83c\uddf7 Argentina", "team2": "\ud83c\udde6\ud83c\uddf9 Austria", "score1": "2", "score2": "0", "played": true}, {"id": "GJ_3", "group": "J", "team1": "\ud83c\udde6\ud83c\uddf7 Argentina", "team2": "\ud83c\uddef\ud83c\uddf4 Jordan", "score1": "3", "score2": "0", "played": true}, {"id": "GJ_4", "group": "J", "team1": "\ud83c\udde9\ud83c\uddff Algeria", "team2": "\ud83c\udde6\ud83c\uddf9 Austria", "score1": "3", "score2": "3", "played": true}, {"id": "GJ_5", "group": "J", "team1": "\ud83c\udde9\ud83c\uddff Algeria", "team2": "\ud83c\uddef\ud83c\uddf4 Jordan", "score1": "2", "score2": "1", "played": true}, {"id": "GJ_6", "group": "J", "team1": "\ud83c\udde6\ud83c\uddf9 Austria", "team2": "\ud83c\uddef\ud83c\uddf4 Jordan", "score1": "3", "score2": "1", "played": true}, {"id": "GK_1", "group": "K", "team1": "\ud83c\uddf5\ud83c\uddf9 Portugal", "team2": "\ud83c\udde8\ud83c\uddf4 Colombia", "score1": "0", "score2": "0", "played": true}, {"id": "GK_2", "group": "K", "team1": "\ud83c\uddf5\ud83c\uddf9 Portugal", "team2": "\ud83c\udde8\ud83c\udde9 DR Congo", "score1": "1", "score2": "1", "played": true}, {"id": "GK_3", "group": "K", "team1": "\ud83c\uddf5\ud83c\uddf9 Portugal", "team2": "\ud83c\uddfa\ud83c\uddff Uzbekistan", "score1": "5", "score2": "0", "played": true}, {"id": "GK_4", "group": "K", "team1": "\ud83c\udde8\ud83c\uddf4 Colombia", "team2": "\ud83c\udde8\ud83c\udde9 DR Congo", "score1": "1", "score2": "0", "played": true}, {"id": "GK_5", "group": "K", "team1": "\ud83c\udde8\ud83c\uddf4 Colombia", "team2": "\ud83c\uddfa\ud83c\uddff Uzbekistan", "score1": "3", "score2": "1", "played": true}, {"id": "GK_6", "group": "K", "team1": "\ud83c\udde8\ud83c\udde9 DR Congo", "team2": "\ud83c\uddfa\ud83c\uddff Uzbekistan", "score1": "1", "score2": "0", "played": true}, {"id": "GL_1", "group": "L", "team1": "\ud83c\udff4\udb40\udc67\udb40\udc62\udb40\udc65\udb40\udc6e\udb40\udc67\udb40\udc7f England", "team2": "\ud83c\udded\ud83c\uddf7 Croatia", "score1": "4", "score2": "2", "played": true}, {"id": "GL_2", "group": "L", "team1": "\ud83c\udff4\udb40\udc67\udb40\udc62\udb40\udc65\udb40\udc6e\udb40\udc67\udb40\udc7f England", "team2": "\ud83c\uddec\ud83c\udded Ghana", "score1": "0", "score2": "0", "played": true}, {"id": "GL_3", "group": "L", "team1": "\ud83c\udff4\udb40\udc67\udb40\udc62\udb40\udc65\udb40\udc6e\udb40\udc67\udb40\udc7f England", "team2": "\ud83c\uddf5\ud83c\udde6 Panama", "score1": "2", "score2": "0", "played": true}, {"id": "GL_4", "group": "L", "team1": "\ud83c\udded\ud83c\uddf7 Croatia", "team2": "\ud83c\uddec\ud83c\udded Ghana", "score1": "1", "score2": "0", "played": true}, {"id": "GL_5", "group": "L", "team1": "\ud83c\udded\ud83c\uddf7 Croatia", "team2": "\ud83c\uddf5\ud83c\udde6 Panama", "score1": "2", "score2": "1", "played": true}, {"id": "GL_6", "group": "L", "team1": "\ud83c\uddec\ud83c\udded Ghana", "team2": "\ud83c\uddf5\ud83c\udde6 Panama", "score1": "1", "score2": "0", "played": true}], "savedAt": 1784051799605}